{
    "head": [
        "bunny",
        "snake",
        "raven",
        "snake",
        "raven",
        "bunny",
        "lion",
        "bull",
        "bunny",
        "raven",
        "raven",
        "bull",
        "snake",
        "bunny",
        "bunny",
        "lion",
        "raven",
        "bunny",
        "snake",
        "raven"
    ],
    "body": [
        "snake-snake",
        "bunny-lion",
        "bunny-bunny",
        "raven-bull",
        "lion-snake",
        "raven-snake",
        "bunny-bunny",
        "bunny-raven",
        "bunny-bunny",
        "lion-raven",
        "lion-snake",
        "snake-raven",
        "raven-lion",
        "snake-bunny",
        "bunny-bunny",
        "bull-bunny",
        "lion-bunny",
        "bull-snake",
        "snake-bull",
        "bull-bull"
    ],
    "tail": [
        5,
        12,
        8,
        14,
        5,
        11,
        12,
        10,
        15,
        12,
        11,
        11,
        7,
        11,
        17,
        11,
        15,
        12,
        11,
        14
    ],
    "arms": [
        2,
        6,
        2,
        8,
        2,
        8,
        6,
        4,
        6,
        6,
        2,
        8,
        4,
        2,
        8,
        8,
        6,
        6,
        2,
        8
    ],
    "legs": [
        3,
        6,
        6,
        6,
        3,
        3,
        6,
        6,
        9,
        6,
        9,
        3,
        3,
        9,
        9,
        3,
        9,
        6,
        9,
        6
    ]
}